odoo10_addon_l10n_br_stock_account-10.0.1.0.1.99.dev24-nspkg.pth
odoo/addons/l10n_br_stock_account/README.rst
odoo/addons/l10n_br_stock_account/__init__.py
odoo/addons/l10n_br_stock_account/__manifest__.py
odoo/addons/l10n_br_stock_account/data/l10n_br_stock_account_data.xml
odoo/addons/l10n_br_stock_account/demo/l10n_br_stock_account_demo.xml
odoo/addons/l10n_br_stock_account/i18n/l10n_br_stock_account.pot
odoo/addons/l10n_br_stock_account/i18n/pt_BR.po
odoo/addons/l10n_br_stock_account/models/__init__.py
odoo/addons/l10n_br_stock_account/models/procurement.py
odoo/addons/l10n_br_stock_account/models/res_company.py
odoo/addons/l10n_br_stock_account/models/stock.py
odoo/addons/l10n_br_stock_account/models/stock_account.py
odoo/addons/l10n_br_stock_account/security/ir.model.access.csv
odoo/addons/l10n_br_stock_account/static/description/icon.png
odoo/addons/l10n_br_stock_account/tests/__init__.py
odoo/addons/l10n_br_stock_account/tests/test_invoicing_picking.py
odoo/addons/l10n_br_stock_account/tests/test_procurement_order.py
odoo/addons/l10n_br_stock_account/views/res_company_view.xml
odoo/addons/l10n_br_stock_account/views/stock_account_view.xml
odoo/addons/l10n_br_stock_account/views/stock_view.xml
odoo/addons/l10n_br_stock_account/wizard/__init__.py
odoo/addons/l10n_br_stock_account/wizard/stock_invoice_onshipping.py
odoo/addons/l10n_br_stock_account/wizard/stock_invoice_onshipping_view.xml
odoo/addons/l10n_br_stock_account/wizard/stock_return_picking.py
odoo/addons/l10n_br_stock_account/wizard/stock_return_picking_view.xml
odoo10_addon_l10n_br_stock_account-10.0.1.0.1.99.dev24.dist-info/METADATA
odoo10_addon_l10n_br_stock_account-10.0.1.0.1.99.dev24.dist-info/WHEEL
odoo10_addon_l10n_br_stock_account-10.0.1.0.1.99.dev24.dist-info/namespace_packages.txt
odoo10_addon_l10n_br_stock_account-10.0.1.0.1.99.dev24.dist-info/top_level.txt
odoo10_addon_l10n_br_stock_account-10.0.1.0.1.99.dev24.dist-info/RECORD
