Metadata-Version: 2.1
Name: odoo10-addon-l10n-br-stock-account
Version: 10.0.1.0.1.99.dev24
Summary: Brazilian Localization WMS Accounting
Home-page: http://odoo-brasil.org
Author: Akretion, Odoo Community Association (OCA)
Author-email: support@odoo-community.org
License: AGPL-3
Platform: UNKNOWN
Classifier: Programming Language :: Python
Classifier: Framework :: Odoo
Classifier: License :: OSI Approved :: GNU Affero General Public License v3
Requires-Python: ~=2.7
Requires-Dist: odoo10-addon-account-fiscal-position-rule-stock
Requires-Dist: odoo10-addon-l10n-br-account-product
Requires-Dist: odoo10-addon-l10n-br-stock
Requires-Dist: odoo (<10.1dev,>=10.0)
